StringMatching/__init__.py
StringMatching/matcher.py
StringMatching-0.0.1.dist-info/LICENSE
StringMatching-0.0.1.dist-info/METADATA
StringMatching-0.0.1.dist-info/WHEEL
StringMatching-0.0.1.dist-info/top_level.txt
StringMatching-0.0.1.dist-info/RECORD
